auth0_auth/__init__.py
auth0_auth/backends.py
auth0_auth/context_processors.py
auth0_auth/middleware.py
auth0_auth/urls.py
auth0_auth/utils.py
auth0_auth/views.py
django2_auth0_auth-4.1.5.dist-info/LICENSE
django2_auth0_auth-4.1.5.dist-info/METADATA
django2_auth0_auth-4.1.5.dist-info/WHEEL
django2_auth0_auth-4.1.5.dist-info/top_level.txt
django2_auth0_auth-4.1.5.dist-info/RECORD
