Metadata-Version: 2.1
Name: django2-auth0-auth
Version: 4.1.5
Summary: Authenticated users using Auth0.
Home-page: https://github.com/ITAMCO/django2-auth0-auth/
Author: Jason Christa
Author-email: jason@zeitcode.com
Maintainer: Kieran Evans
Maintainer-email: keyz182@gmail.com
License: UNKNOWN
Platform: UNKNOWN
Classifier: Environment :: Web Environment
Classifier: License :: OSI Approved :: BSD License
Classifier: Framework :: Django
Classifier: Programming Language :: Python
Requires-Dist: PyJWT (>=1.1.0)
Requires-Dist: requests (>=2.0.0)
Requires-Dist: django (>=2.0.0)
Requires-Dist: python-jose (>=3.0.0)
Requires-Dist: iso8601 (==0.1.12)
